colabtools/__init__.py
colabtools/config.py
colabtools/utils.py
colab_dev_tools-0.0.10.dist-info/LICENSE
colab_dev_tools-0.0.10.dist-info/METADATA
colab_dev_tools-0.0.10.dist-info/WHEEL
colab_dev_tools-0.0.10.dist-info/top_level.txt
colab_dev_tools-0.0.10.dist-info/RECORD
