Metadata-Version: 2.1
Name: colab-dev-tools
Version: 0.0.10
Summary: Python utils package for Google Colab
Home-page: https://github.com/namiyousef/colab-utils
Author: Yousef Nami
Author-email: namiyousef@hotmail.com
License: MIT
Platform: UNKNOWN
License-File: LICENSE
Requires-Dist: torch
Requires-Dist: numpy
Requires-Dist: nvidia-ml-py3
